<?xml version="1.0" encoding="UTF-8"?>
<actions>
        <action>
            <actionName>build-with-dependencies</actionName>
            <reactor>also-make</reactor>
            <packagings>
                <packaging>*</packaging>
            </packagings>
            <goals>
                <goal>install</goal>
            </goals>
            <properties>
                <skipTests>true</skipTests>
            </properties>
        </action>
        <action>
            <actionName>run</actionName>
            <packagings>
                <packaging>jar</packaging>
            </packagings>
            <goals>
                <goal>spring-boot:run</goal>
                
            </goals>
            <properties>
                <spring-boot.run.jvmArguments>-noverify -XX:TieredStopAtLevel=1 -Dspring.profiles.active=hml</spring-boot.run.jvmArguments>
                <spring-boot.run.mainClass>com.core.matrix.MatrixApplication</spring-boot.run.mainClass>
                <Env.SPRING_OUTPUT_ANSI_ENABLED>always</Env.SPRING_OUTPUT_ANSI_ENABLED>
                
                
            </properties>
        </action>
    </actions>
